[
   {
      "name":"Stretch",
      "model":2333339779,
      "power":30,
      "speed":170,
      "combustion":9,
      "tank":40,
      "trunk":[
         3,
         3
      ],
      "probability":3,
      "price":643200,
      "mechfactor":19296,
      "visufactor":6432,
      "extra":1
   },
   {
      "name":"Dune Explorer",
      "model":534258863,
      "power":50,
      "speed":190,
      "combustion":10,
      "tank":40,
      "trunk":[
         3,
         3
      ],
      "probability":5,
      "price":1,
      "mechfactor":0,
      "visufactor":0,
      "extra":-1
   },
   {
      "name":"Toreador",
      "model":1455990255,
      "power":30,
      "speed":200,
      "combustion":12,
      "tank":35,
      "trunk":[
         4,
         4
      ],
      "probability":1,
      "price":882400,
      "mechfactor":26472,
      "visufactor":26472,
      "extra":-1
   },
   {
      "name":"Deluxo",
      "model":1483171323,
      "power":45,
      "speed":207,
      "combustion":14,
      "tank":35,
      "trunk":[
         4,
         4
      ],
      "probability":1,
      "price":930400,
      "mechfactor":46520,
      "visufactor":9304,
      "extra":-1
   },
   {
      "name":"Monster",
      "model":3449006043,
      "power":30,
      "speed":160,
      "combustion":16,
      "tank":40,
      "trunk":[
         2,
         2
      ],
      "probability":5,
      "price":1,
      "mechfactor":0,
      "visufactor":0,
      "extra":-1
   },
   {
      "name":"Hotring",
      "model":1115909093,
      "power":33,
      "speed":210,
      "combustion":15,
      "tank":40,
      "trunk":[
         3,
         3
      ],
      "probability":1,
      "price":830200,
      "mechfactor":24906,
      "visufactor":24906,
      "extra":-1
   },
   {
      "name":"Patriot Stretch",
      "model":3874056184,
      "power":30,
      "speed":164,
      "combustion":10,
      "tank":40,
      "trunk":[
         5,
         5
      ],
      "probability":5,
      "price":543000,
      "mechfactor":16290,
      "visufactor":5430,
      "extra":-1
   },
   {
      "name":"Elegy Retro Retro",
      "model":3354509874,
      "power":33,
      "speed":220,
      "combustion":10,
      "tank":40,
      "trunk":[
         5,
         5
      ],
      "probability":5,
      "price":543000,
      "mechfactor":16290,
      "visufactor":5430,
      "extra":-1
   },
   {
      "name":"Buffalo Retro",
      "model":333348457,
      "power":40,
      "speed":240,
      "combustion":10,
      "tank":40,
      "trunk":[
         5,
         5
      ],
      "probability":5,
      "price":543000,
      "mechfactor":16290,
      "visufactor":5430,
      "extra":-1
   },
   {
      "name":"Buffalo Police",
      "model":2667966721,
      "power":100,
      "speed":245,
      "combustion":9,
      "tank":40,
      "trunk":[
         8,
         8
      ],
      "probability":5,
      "price":53000,
      "mechfactor":16290,
      "visufactor":5430,
      "extra":-1
   },
   {
      "name":"Torrence Police",
      "model":1912215274,
      "power":70,
      "speed":225,
      "combustion":8,
      "tank":40,
      "trunk":[
         8,
         8
      ],
      "probability":5,
      "price":53000,
      "mechfactor":16290,
      "visufactor":5430,
      "extra":-1
   },
   {
      "name":"Stanier Police",
      "model":2046537925,
      "power":80,
      "speed":195,
      "combustion":7,
      "tank":40,
      "trunk":[
         8,
         8
      ],
      "probability":5,
      "price":53000,
      "mechfactor":16290,
      "visufactor":5430,
      "extra":-1
   },
   {
      "name":"Comet Police",
      "model":110006315,
      "power":30,
      "speed":290,
      "combustion":12,
      "tank":40,
      "trunk":[
         8,
         8
      ],
      "probability":5,
      "price":53000,
      "mechfactor":16290,
      "visufactor":5430,
      "extra":-1
   },
   {
      "name":"Gresley Police",
      "model":2620582743,
      "power":85,
      "speed":230,
      "combustion":9,
      "tank":40,
      "trunk":[
         8,
         8
      ],
      "probability":5,
      "price":53000,
      "mechfactor":16290,
      "visufactor":5430,
      "extra":-1
   },
   {
      "name":"Dominator Police",
      "model":1802203865,
      "power":50,
      "speed":232,
      "combustion":9,
      "tank":40,
      "trunk":[
         8,
         8
      ],
      "probability":5,
      "price":53000,
      "mechfactor":16290,
      "visufactor":5430,
      "extra":-1
   }
]